{"id":"20220328_053955_ssc1d1_0021","type":"Feature","geometry":{"coordinates":[[[75.57067521000785,15.348739277038137],[75.56368645767863,15.352562645853391],[75.5542950048749,15.33653312333],[75.5612741503644,15.332702396129148],[75.57067521000785,15.348739277038137]]],"type":"Polygon"},"properties":{"acquired":"2022-03-28T05:39:55.375Z","camera_id":"d1","clear_confidence_percent":67,"clear_percent":54,"cloud_cover":0,"cloud_percent":0,"ground_control":true,"gsd":0.64,"heavy_haze_percent":0,"item_type":"SkySatScene","light_haze_percent":46,"pixel_resolution":0.5,"provider":"skysat","published":"2022-03-28T12:24:50Z","publishing_stage":"finalized","quality_category":"standard","satellite_azimuth":70.4,"satellite_id":"SSC1","shadow_percent":0,"snow_ice_percent":0,"strip_id":"s3_20220328T053955Z","sun_azimuth":119.1,"sun_elevation":66.2,"updated":"2022-03-29T05:42:57Z","view_angle":3.9,"visible_confidence_percent":65,"visible_percent":100}}
